djib/__init__.py
djib/constants.py
djib/dtypes.py
djib/kms.py
djib/rpc.py
djib-0.1.2.dist-info/LICENSE
djib-0.1.2.dist-info/WHEEL
djib-0.1.2.dist-info/METADATA
djib-0.1.2.dist-info/RECORD
