Metadata-Version: 2.1
Name: djib
Version: 0.1.2
Summary: Djib Python API
Home-page: https://djib.io
License: GPL-3.0-only
Keywords: blockchain,command-line-tools,p2p-network,solana,djib
Author: Djib tech team
Author-email: tech@djib.io
Requires-Python: >=3.10,<4.0
Classifier: Intended Audience :: Developers
Classifier: License :: OSI Approved :: GNU General Public License v3 (GPLv3)
Classifier: Natural Language :: English
Classifier: Programming Language :: Python :: 3
Classifier: Programming Language :: Python :: 3.10
Requires-Dist: PyNaCl (>=1.5.0,<2.0.0)
Requires-Dist: base58 (>=2.1.1,<3.0.0)
Requires-Dist: jsonrpcserver (>=5.0.8,<6.0.0)
Requires-Dist: python-magic (>=0.4.27,<0.5.0)
Requires-Dist: solana (>=0.25.1,<0.26.0)
Project-URL: Documentation, https://docs.djib.io
